{"components_chacao.md":"5e2cb337","components_canshu.md":"62d0678f","components_leixing.md":"c466fa8a","components_defaultstate.md":"15b85e52","components_color.md":"079d56c8","components_customicon.md":"83b701c7","components_shijian.md":"9128891e","components_disabledstate.md":"9841d290","components_drag.md":"ad4b836b","components_lazyload.md":"38c275c6","index.md":"84dbd409","components_accordion.md":"ec4f251b","components_basic.md":"373f12a0","components_treefactory.md":"bd839665","components_checkboxpos.md":"e19b237f","others_license.md":"a1b6117d","guide_design.md":"82ed977f","components_check.md":"6d2833b6","guide_faq.md":"5e23f8ff","components_mergenode.md":"432e9431","components_virtualscroll.md":"5b0c6295","components_showline.md":"1a13ec86","components_contextmenu.md":"f3bc2e83","others_todo.md":"12c364f4","components_treenode.md":"8ad3a196","others_changelog.md":"5edbe9bb","guide_guide.md":"717c573e","guide_installation.md":"62b9e61e","guide_quickstart.md":"c5d27784","components_openall.md":"40654457","components_search.md":"336082c6","components_operate.md":"a663ae84"}
